{"records": [{"_url": "https://channeladvisorimages2.s3.us-east-2.amazonaws.com/AP-06_PHOTO.JPEG", "Top Category": "Clothing", "region": "generic", "_status": {"code": 200, "text": "OK", "request_id": "7c1c25cb-3691-4d15-8564-81f6cdeac8c3"}, "_id": "7690592f-0fbd-4023-8b1f-fa1b8b066314", "_width": 1536, "_height": 2048, "_tags": {"Category": [{"prob": 0.75949, "name": "Clothing/Jackets and Coats", "id": "8197f0fa-4944-4f53-ac72-527a6247d80c"}], "Color": [{"prob": 0.41468, "name": "multicolor", "id": "d2b6c02c-f84b-444a-b4cd-bc2d49b8e529"}, {"prob": 0.35198, "name": "black", "id": "9346545f-13e8-43c6-85b3-eab4a2319020"}], "Gender": [{"prob": 0.54121, "name": "women", "id": "cc58c8ea-17a1-4caf-871b-3953a5ff4c3e"}], "Length": [{"prob": 0.9906, "name": "short", "id": "f4d10afd-3d64-42b0-aec1-b0ad3adbbf16"}], "Material": [{"prob": 0.61026, "name": "synthetic", "id": "e4fcd722-f00f-4d06-a6fd-2f0d48f1fd8e"}, {"prob": 0.43098, "name": "softshell", "id": "5acd40e9-8d1e-4be4-ac8f-15c06f8bc7ab"}], "Style": [{"prob": 0.95384, "name": "casual", "id": "b2258131-2448-45e2-b7a2-e28838b7a4be"}], "Age": [{"prob": 0.75027, "name": "adult", "id": "464f18b8-e61b-4f95-afe6-48b3a8db26ab"}], "Design": [{"prob": 0.8466, "name": "logo", "id": "646f8090-2edf-4c2e-b0ad-71edf9342ed3"}], "Closure": [{"prob": 0.97991, "name": "full closure", "id": "9b23d104-660c-4eaf-8e57-5bb8e981e682"}], "Fastening": [{"prob": 0.97515, "name": "fastening", "id": "59fc9b5a-c95b-409f-83c6-83a5bc462f3a"}], "Fastening type": [{"prob": 0.99165, "name": "zipper", "id": "b481a104-bcea-4898-b9db-d677276f4274"}], "Belt": [{"prob": 0.97962, "name": "no belt", "id": "c0069c57-18a4-41a4-8fe2-d26fd1202122"}], "Fit": [{"prob": 0.73255, "name": "Regular", "id": "4757c51e-19a1-4cbb-9eb6-5a660e757a28"}], "Pockets": [{"prob": 0.98888, "name": "Pockets", "id": "ed4bb202-f3cc-4e98-8482-b890132e534a"}], "Type": [{"prob": 0.95679, "name": "Sleeve pocket", "id": "ab618f5d-940a-49f9-8a2f-b88b8e4b440d"}, {"prob": 0.87319, "name": "Front", "id": "9a54e521-a42f-403b-9c85-6c98bb541567"}], "Location": [{"prob": 0.98131, "name": "Upper pockets", "id": "d1f65631-02ba-48bd-8723-394a41eb2743"}], "Top Category": [{"name": "Clothing", "prob": 1.0, "id": "13052be8-2cc7-48e4-a782-a00d658f997c", "pre-filled": true}]}, "_tags_simple": ["adult", "full closure", "synthetic", "Sleeve pocket", "fastening", "Clothing", "short", "no belt", "Clothing/Jackets and Coats", "logo", "zipper", "Regular", "women", "Pockets", "casual", "Upper pockets", "Front"], "_tags_map": {"Category": "Clothing/Jackets and Coats", "Color": "multicolor", "Gender": "women", "Length": "short", "Material": "synthetic", "Style": "casual", "Age": "adult", "Design": "logo", "Closure": "full closure", "Fastening": "fastening", "Fastening type": "zipper", "Belt": "no belt", "Fit": "Regular", "Pockets": "Pockets", "Type": "Sleeve pocket", "Location": "Upper pockets", "Top Category": "Clothing"}, "Category": "Clothing/Jackets and Coats"}], "version": "2025-04-10 10:36:30.177913+00:00", "model_format": "", "calls": [], "status": {"code": 200, "text": "OK", "request_id": "7c1c25cb-3691-4d15-8564-81f6cdeac8c3", "proc_id": "73322abc-258b-4b32-967a-c7bfc9aaa2a2"}, "statistics": {"processing time": 1.7380080223083496}}