{"records": [{"_url": "https://channeladvisorimages2.s3.us-east-2.amazonaws.com/AP-43_PHOTO.JPEG", "Top Category": "Clothing", "region": "generic", "_status": {"code": 200, "text": "OK", "request_id": "e2f24327-9661-47fa-91e1-c705164fbca1"}, "_id": "66416d7e-4e6c-4d58-b07a-af78e336e72b", "_width": 1536, "_height": 2048, "_tags": {"Category": [{"prob": 0.46402, "name": "Clothing/Upper", "id": "fe984081-9c79-44ed-bf48-6e0075066e17"}], "Top Category": [{"name": "Clothing", "prob": 1.0, "id": "13052be8-2cc7-48e4-a782-a00d658f997c", "pre-filled": true}]}, "_tags_simple": ["Clothing/Upper", "Clothing"], "_tags_map": {"Category": "Clothing/Upper", "Top Category": "Clothing"}, "Category": "Clothing/Upper"}], "version": "2025-04-10 10:36:30.177913+00:00", "model_format": "", "calls": [], "status": {"code": 200, "text": "OK", "request_id": "e2f24327-9661-47fa-91e1-c705164fbca1", "proc_id": "73322abc-258b-4b32-967a-c7bfc9aaa2a2"}, "statistics": {"processing time": 1.313985824584961}}